py3js/__init__.py
py3js/d3v6.html
py3js/force.html
py3js/infra.py
py3js/network.py
py3js/tree.py
py3js/visualisation.py
py3js/wordcloud.html
py3js/wordcloud.py
py3js-0.9.10.dist-info/LICENSE
py3js-0.9.10.dist-info/METADATA
py3js-0.9.10.dist-info/WHEEL
py3js-0.9.10.dist-info/top_level.txt
py3js-0.9.10.dist-info/RECORD
