Metadata-Version: 2.1
Name: py3js
Version: 0.9.10
Summary: Python library to plot force-directed graphs, trees, wordclouds and so on, using D3JS library.
Home-page: https://github.com/aloneguid/py3js
Author: Ivan Gavryliuk
Author-email: aloneguid@outlook.com
License: Apache-2.0
License-File: LICENSE
